[{
  "_id": {
    "$oid": "6697644f4b8318c27ffba146"
  },
  "Pilier": "Transformation structurelle de l'économie",
  "SousPilier": {
    "Développement des industries et des services": {
      "1": "Industrie de l'énergie",
      "2": "Agro-industrie",
      "3": "Numérique",
      "4": "Forêt-Bois",
      "5": "Textle-Confection-Cuir",
      "6": "Mines-Métallurgie-Sidérurgie",
      "7": "Hydrocarbures-Raffinage-Pétrochimie",
      "8": "Chimie-Pharmacie",
      "9": "Construction-Services-Professionnels-Scientifiques-Techniques",
      "10": "Développement des services non financiers"
    },
    "Développement de la productivité et de la production agricoles": {
      "1": "Accroissement de la productivité, de la production et de la compétitivité des produits agro-sylvo-pastoraux et halieutiques",
      "2": "Accès à la terre, aux équipements et infrastructures de production",
      "3": "Structuration et renforcement des capacités des acteurs"
    },
    "développement des infrastructures productives": {
      "1": "Infrastructures énergétiques",
      "2": "Infrastructures de transport",
      "3": "Infrastructures de télécommunications",
      "4": "Infrastructures hydrauliques et d'assainissement",
      "5": "Modernisation urbaine",
      "6": "Gestion domaniale et cadastrale"
    },
    "Intégration régionale et facilitation des échanges": {
      "1": "Intégration régionale",
      "2": "Facilitation des échanges"
    },
    "Dynamisation du secteur privé": {
      "1": "Rattrapage et développement technologique",
      "2": "Incitations au développement des entreprises",
      "3": "Protection de l'espace économique national"
    },
    "Environnement et protection de la nature": {
      "1": "Gestion durable des ressources naturelles",
      "2": "Adaptation aux changements climatiques"
    },
    "Transformation du système financier": {
      "1": "Accroissement de l'inclusion financière et densification du système financier et banquaire",
      "2": "Développement du financement local des investissements et des exportations",
      "3": "Renforcement du financement régional et international des investissements et des exportations",
      "4": "Développement du crédit fournisseur",
      "5": "Mobilisation des financements de la diaspora et rapatriement des capitaux",
      "6": "Développement des talents et compétences financières"
    }
  }
},
{
  "_id": {
    "$oid": "6697ddb14b8318c27ffba14f"
  },
  "Pilier": "DEVELOPPEMENT DU CAPITAL HUMAIN ET DU BIEN-ÊTRE",
  "SousPilier": {
    "Contexte démographique": {},
    "Education, formation et employabilité": {
      "1": "Accès et équité",
      "2": "Qualité, employabilité et entreprenariabilité",
      "3": "Renforcement du système éducatif"
    },
    "Santé et nutrition": {
      "1": "Promotion de la santé et de la nutrition",
      "2": "Prévention de la maladie",
      "3": "Prise en charge des cas",
      "4": "Renforcement du système de santé"
    },
    "Accès aux facultés sociales de base": {
      "1": "Accès à l'habitat",
      "2": "Accès à l'eau potable",
      "3": "Accès à l'électricité"
    },
    "Protection sociale": {
      "1": "Sécurité sociale",
      "2": "Tranferts sociaux",
      "3": "Action sociale",
      "4": "Promotion du genre et de l'équité",
      "5": "Communication pour le développement social"
    },
    "Recherche; développement et innovation": {}
  }
},
{
  "_id": {
    "$oid": "6697de854b8318c27ffba150"
  },
  "Pilier": "PROMOTION DE L'EMPLOI ET INSERTION ECONOMIQUE",
  "SousPilier": {
    "Promotion de l'emploi dans les projets d'investissement public": {},
    "Productivité agricole, emploi et revenus en milieu rural": {},
    "Développement des TPE, PME et de l'entrepreneuriat jeunes en zones urbaines": {},
    "Création et préservation de l'emploi décent dans les grandes entreprises": {},
    "Mise en adéquation formation-emploi et insertion professionnelle": {},
    "Régulation du marché du travail": {}
  }
},
{
  "_id": {
    "$oid": "6697deae4b8318c27ffba151"
  },
  "Pilier": "GOUVERNANCE, DECENTRALISATION ET GESTION STRATEGIQUE DE L'ETAT",
  "SousPilier": {
    "Décentralisation et développement local": {},
    "Renforcement de l'état de droit et sécurité des personnes et des biens": {
      "1": "Renforcement de l'état de droit et protection des droits humains",
      "2": "Consolidation du pouvoir judiciaire et accès de tous à une justice équiable",
      "3": "Intensification de la lutte contre l'insécurité, la criminalité et le terrorisme",
      "4": "Prévention et gestion des crises",
      "5": "Amélioration de la communication institutionnelle et de l'accès à l'information publique"
    },
    "Amélioration du service public de l'état": {
      "1": "Modernisation de l'administration publique",
      "2": "Optimisation du fonctionnement de l'administration publique",
      "3": "Amélioration de la gestion des ressources humaines de l'état",
      "4": "Renforcement de la lutte contre la corruption, les détournements de fonds et les conflits d'intéret"
    },
    "Gouvernance économique et financière": {
      "1": "Modernisation de la gestion des finances publiques",
      "2": "Amélioration de la gestion de la dette",
      "3": "Rationalisation de la gestion des établissements et entreprises publics",
      "4": "Amélioration du climat des affaires",
      "5": "Renforcement de la coopération et du partenariat au développement",
      "6": "Contribution de la disapora au développement et apport de la diplomatie économique",
      "7": "Régulation et surveillance de l'espace économique national"
    },
    "Aménagement du territoire": {},
    "Promotion du bilinguisme, du multiculturalisme et de la citoyenneté": {
      "1": "Promotion du bilinguisme",
      "2": "Promotion du multiculturalisme et développement d'une identité culturelle synthétique",
      "3": "Réappropriation de la citoyenneté et du patriotisme",
      "4": "Raffermissement du lien social, de l'autorité de l'Etat et du rapport Etat-citoyen"
    }
  }
}]